zt_dlipower/__init__.py
zt_dlipower/dlipower.py
zt_dlipower/scripts/__init__.py
zt_dlipower/scripts/dlipower.py
zt_dlipower/scripts/fence_dli.py
zt_dlipower-1.1.0.dist-info/LICENSE.txt
zt_dlipower-1.1.0.dist-info/METADATA
zt_dlipower-1.1.0.dist-info/WHEEL
zt_dlipower-1.1.0.dist-info/entry_points.txt
zt_dlipower-1.1.0.dist-info/RECORD
